LICENSE
MANIFEST.in
README.rst
setup.py
dpauth/__init__.py
dpauth/apps.py
dpauth/conf.py
dpauth/urls.py
dpauth/utils.py
dpauth.egg-info/PKG-INFO
dpauth.egg-info/SOURCES.txt
dpauth.egg-info/dependency_links.txt
dpauth.egg-info/requires.txt
dpauth.egg-info/top_level.txt
dpauth/serializers/__init__.py
dpauth/serializers/signup.py
dpauth/views/__init__.py
dpauth/views/signup.py